keepassxc_cli_integration/__init__.py
keepassxc_cli_integration/backend/__init__.py
keepassxc_cli_integration/backend/kpx_protocol/__init__.py
keepassxc_cli_integration/backend/kpx_protocol/classes.py
keepassxc_cli_integration/backend/kpx_protocol/classes_requests.py
keepassxc_cli_integration/backend/kpx_protocol/classes_responses.py
keepassxc_cli_integration/backend/kpx_protocol/connection_config.py
keepassxc_cli_integration/backend/kpx_protocol/errors.py
keepassxc_cli_integration/backend/kpx_protocol/kpx_protocol.py
keepassxc_cli_integration/backend/kpx_protocol/settings.py
keepassxc_cli_integration/backend/kpx_protocol/winpipe.py
keepassxc_cli_integration/backend/old_modules.py
keepassxc_cli_integration/backend/queries.py
keepassxc_cli_integration/backend/run_command.py
keepassxc_cli_integration/backend/settings.py
keepassxc_cli_integration/backend/string_query.py
keepassxc_cli_integration/backend/utils.py
keepassxc_cli_integration/kpx.py
keepassxc_cli_integration/kpx_cmd.py
keepassxc_cli_integration-1.4.0.dist-info/entry_points.txt
keepassxc_cli_integration-1.4.0.dist-info/LICENSE
keepassxc_cli_integration-1.4.0.dist-info/METADATA
keepassxc_cli_integration-1.4.0.dist-info/WHEEL
keepassxc_cli_integration-1.4.0.dist-info/RECORD
