Metadata-Version: 2.3
Name: keepassxc-cli-integration
Version: 1.4.0
Summary: CLI integration for KeepassXC GUI.
License: Apache License
Keywords: keepassxc,keepassxc-cli,keepass,password manager
Author: oevergodofchaos
Author-email: vezonzzzzzz@gmail.com
Requires-Python: >=3.10
Classifier: License :: Other/Proprietary License
Classifier: Programming Language :: Python :: 3
Classifier: Programming Language :: Python :: 3.10
Classifier: Programming Language :: Python :: 3.11
Classifier: Programming Language :: Python :: 3.12
Classifier: Programming Language :: Python :: 3.13
Requires-Dist: PyNaCl (>=1.5.0,<2.0.0)
Requires-Dist: cffi (>=1.17.0,<2.0.0)
Requires-Dist: click (>=8.2.1)
Requires-Dist: pycparser (>=2.20,<3.0)
Requires-Dist: pydantic (>=2.11.9,<3.0.0)
Requires-Dist: pywin32 (>=308) ; sys_platform == "win32"
Requires-Dist: toml (>=0.10.0,<1.0.0)
Requires-Dist: typer (>=0.16.0)
Requires-Dist: websockets (>=15.0)
